compsyn/__init__.py
compsyn/analysis.py
compsyn/color.py
compsyn/config.py
compsyn/datahelper.py
compsyn/helperfunctions.py
compsyn/jzazbz.py
compsyn/logger.py
compsyn/s3.py
compsyn/texture.py
compsyn/trial.py
compsyn/utils.py
compsyn/vector.py
compsyn/vectors.py
compsyn/visualisation.py
compsyn/wordnet_functions.py
compsyn/wordtocolor_vector.py
compsyn-1.0.2.dist-info/METADATA
compsyn-1.0.2.dist-info/LICENSE
compsyn-1.0.2.dist-info/WHEEL
compsyn-1.0.2.dist-info/RECORD
